{
    "gitignore": {
        "branch": "master",
        "description": "Nix function for filtering local git sources",
        "homepage": "",
        "owner": "hercules-ci",
        "repo": "gitignore",
        "rev": "dcd0b0e878009ef7b1425f8ca3e5b883f12459d8",
        "sha256": "0ni9hl6j4l94mfwsdmrg5l0ffibfgd8amspda7vc5fb3wm8blxpy",
        "type": "tarball",
        "url": "https://github.com/hercules-ci/gitignore/archive/dcd0b0e878009ef7b1425f8ca3e5b883f12459d8.tar.gz",
        "url_template": "https://github.com/<owner>/<repo>/archive/<rev>.tar.gz"
    },
    "niv": {
        "branch": "master",
        "description": "Easy dependency management for Nix projects",
        "homepage": "https://github.com/nmattia/niv",
        "owner": "nmattia",
        "repo": "niv",
        "rev": "6f03879b8a91fb0c33c7186da347b914deee3efc",
        "sha256": "04pl8b4gnbfakapjskm4030qlklwzjk0x45jn9gcnjpdl7s8ri33",
        "type": "tarball",
        "url": "https://github.com/nmattia/niv/archive/6f03879b8a91fb0c33c7186da347b914deee3efc.tar.gz",
        "url_template": "https://github.com/<owner>/<repo>/archive/<rev>.tar.gz"
    },
    "nixpkgs": {
        "branch": "master",
        "description": "Pinned Nixpkgs tree (master follows nixos-unstable-small, only tags have stable history)",
        "homepage": "",
        "owner": "serokell",
        "repo": "nixpkgs",
        "rev": "ae37a09824fc5d66af36da64f900532b0df5215a",
        "sha256": "0v4cwbyhja50ksqvcdy1my0kj5033q7wxmplxk82z7k0wf4q2pwn",
        "type": "tarball",
        "url": "https://github.com/serokell/nixpkgs/archive/ae37a09824fc5d66af36da64f900532b0df5215a.tar.gz",
        "url_template": "https://github.com/<owner>/<repo>/archive/<rev>.tar.gz"
    }
}
